malloy_publisher_client/__init__.py
malloy_publisher_client/api_client.py
malloy_publisher_client/models.py
malloy_publisher_client/py.typed
malloy_publisher_client-0.1.1.dist-info/METADATA
malloy_publisher_client-0.1.1.dist-info/WHEEL
malloy_publisher_client-0.1.1.dist-info/licenses/LICENSE
malloy_publisher_client-0.1.1.dist-info/RECORD
