Metadata-Version: 2.4
Name: malloy_publisher_client
Version: 0.1.1
Summary: A Python client for the Malloy Publisher API
Project-URL: Homepage, https://github.com/namabile/malloy-publisher-client
Project-URL: Repository, https://github.com/namabile/malloy-publisher-client
Project-URL: Documentation, https://github.com/namabile/malloy-publisher-client#readme
Project-URL: Bug Tracker, https://github.com/namabile/malloy-publisher-client/issues
Author-email: Nick Amabile <nick.amabile@gmail.com>
License: MIT License
License-File: LICENSE
Keywords: api,client,malloy,publisher
Classifier: Development Status :: 4 - Beta
Classifier: Intended Audience :: Developers
Classifier: License :: OSI Approved :: MIT License
Classifier: Programming Language :: Python :: 3
Classifier: Programming Language :: Python :: 3.11
Classifier: Topic :: Software Development :: Libraries :: Python Modules
Requires-Python: >=3.11
Requires-Dist: httpx>=0.28.1
Requires-Dist: pydantic>=2.0.0
Provides-Extra: dev
Requires-Dist: black>=24.0.0; extra == 'dev'
Requires-Dist: mypy>=1.8.0; extra == 'dev'
Requires-Dist: pydantic>=2.0.0; extra == 'dev'
Requires-Dist: ruff>=0.3.0; extra == 'dev'
